{"tile": "poi-tile-29--91", "lat": 29, "lon": -91, "stations": [{"id": "osm-3686250831", "name": "EV Charging Station", "type": "charging_station", "lat": 29.947719, "lon": -90.074926, "operator": "Unknown", "address": {"street": "", "housenumber": "", "postcode": "", "city": "", "state": "", "country": ""}, "power": {"max_kw": null, "sockets": [{"type": "Chademo", "kw": null, "count": 1}], "capacity": 1}, "source": "osm", "tags": {"fee": "", "access": "", "opening_hours": "24/7", "authentication": "", "brand": "", "network": "", "operator": ""}, "amenities": {"fee": false}}, {"id": "osm-3686257575", "name": "EV Charging Station", "type": "charging_station", "lat": 29.920413, "lon": -90.117412, "operator": "Unknown", "address": {"street": "", "housenumber": "", "postcode": "", "city": "", "state": "", "country": ""}, "power": {"max_kw": null, "sockets": [{"type": "Type1", "kw": null, "count": 1}], "capacity": 1}, "source": "osm", "tags": {"fee": "", "access": "", "opening_hours": "", "authentication": "", "brand": "", "network": "", "operator": ""}, "amenities": {"fee": false}}, {"id": "osm-3686260864", "name": "ChargePoint", "type": "charging_station", "lat": 29.967287, "lon": -90.085007, "operator": "ChargePoint", "address": {"street": "", "housenumber": "", "postcode": "", "city": "", "state": "", "country": ""}, "power": {"max_kw": null, "sockets": [{"type": "Nema 5 20", "kw": null, "count": 2}, {"type": "Type1", "kw": null, "count": 2}], "capacity": 4}, "source": "osm", "tags": {"fee": "", "access": "", "opening_hours": "", "authentication": "", "brand": "ChargePoint", "network": "", "operator": "ChargePoint"}, "amenities": {"fee": false}}, {"id": "osm-3686269259", "name": "ChargePoint", "type": "charging_station", "lat": 29.983083, "lon": -90.257127, "operator": "ChargePoint", "address": {"street": "", "housenumber": "", "postcode": "", "city": "", "state": "", "country": ""}, "power": {"max_kw": null, "sockets": [{"type": "Nema 5 20", "kw": null, "count": 3}, {"type": "Type1", "kw": null, "count": 3}], "capacity": 6}, "source": "osm", "tags": {"fee": "", "access": "", "opening_hours": "", "authentication": "", "brand": "ChargePoint", "network": "", "operator": "ChargePoint"}, "amenities": {"fee": false}}, {"id": "osm-6563505485", "name": "greyhound", "type": "charging_station", "lat": 29.945871, "lon": -90.078878, "operator": "greyhound", "address": {"street": "", "housenumber": "", "postcode": "", "city": "", "state": "", "country": ""}, "power": {"max_kw": null, "sockets": [], "capacity": 0}, "source": "osm", "tags": {"fee": "", "access": "", "opening_hours": "", "authentication": "", "brand": "", "network": "", "operator": "greyhound"}, "amenities": {"fee": false}}, {"id": "osm-12944743371", "name": "New Orleans Supercharger", "type": "charging_station", "lat": 29.95706, "lon": -90.07668, "operator": "Tesla", "address": {"street": "Canal Street", "housenumber": "1500", "postcode": "70112", "city": "New Orleans", "state": "LA", "country": "US"}, "power": {"max_kw": null, "sockets": [{"type": "Nacs", "kw": null, "count": 12}], "capacity": 12}, "source": "osm", "tags": {"fee": "yes", "access": "customers", "opening_hours": "24/7", "authentication": "", "brand": "Tesla Supercharger", "network": "Supercharger", "operator": "Tesla, Inc."}, "amenities": {"fee": true}}], "count": 6}