{"tile": "poi-tile-43-77", "lat": 43, "lon": 77, "stations": [{"id": "osm-11204400838", "name": "EV Charging Station", "type": "charging_station", "lat": 43.432672, "lon": 77.026759, "operator": "Unknown", "address": {"street": "", "housenumber": "", "postcode": "", "city": "", "state": "", "country": ""}, "power": {"max_kw": null, "sockets": [], "capacity": 0}, "source": "osm", "tags": {"fee": "", "access": "", "opening_hours": "", "authentication": "", "brand": "", "network": "", "operator": ""}, "amenities": {"fee": false}}, {"id": "osm-12211921375", "name": "Газпромнефть", "type": "charging_station", "lat": 43.322915, "lon": 77.020347, "operator": "Unknown", "address": {"street": "", "housenumber": "", "postcode": "", "city": "", "state": "", "country": ""}, "power": {"max_kw": null, "sockets": [], "capacity": 0}, "source": "osm", "tags": {"fee": "yes", "access": "customers", "opening_hours": "", "authentication": "", "brand": "Газпромнефть", "network": "", "operator": ""}, "amenities": {"fee": true}}, {"id": "osm-12655872720", "name": "Blue Sky Energy", "type": "charging_station", "lat": 43.163301, "lon": 77.051505, "operator": "Blue Sky Energy", "address": {"street": "", "housenumber": "", "postcode": "", "city": "", "state": "", "country": ""}, "power": {"max_kw": null, "sockets": [], "capacity": 0}, "source": "osm", "tags": {"fee": "", "access": "", "opening_hours": "", "authentication": "", "brand": "Blue Sky Energy", "network": "", "operator": "Blue Sky Energy"}, "amenities": {"fee": false}}, {"id": "osm-12972871319", "name": "eDrive.kz", "type": "charging_station", "lat": 43.171635, "lon": 77.036123, "operator": "Unknown", "address": {"street": "", "housenumber": "", "postcode": "", "city": "", "state": "", "country": ""}, "power": {"max_kw": null, "sockets": [], "capacity": 0}, "source": "osm", "tags": {"fee": "yes", "access": "", "opening_hours": "", "authentication": "", "brand": "", "network": "", "operator": ""}, "amenities": {"fee": true}}, {"id": "osm-13369268469", "name": "Arilan Energy", "type": "charging_station", "lat": 43.32091, "lon": 77.013886, "operator": "Unknown", "address": {"street": "", "housenumber": "", "postcode": "", "city": "", "state": "", "country": ""}, "power": {"max_kw": null, "sockets": [], "capacity": 0}, "source": "osm", "tags": {"fee": "yes", "access": "", "opening_hours": "", "authentication": "", "brand": "", "network": "", "operator": ""}, "amenities": {"fee": true}}, {"id": "osm-13369268470", "name": "Arilan Energy", "type": "charging_station", "lat": 43.331466, "lon": 77.017349, "operator": "Unknown", "address": {"street": "", "housenumber": "", "postcode": "", "city": "", "state": "", "country": ""}, "power": {"max_kw": null, "sockets": [], "capacity": 0}, "source": "osm", "tags": {"fee": "yes", "access": "", "opening_hours": "", "authentication": "", "brand": "", "network": "", "operator": ""}, "amenities": {"fee": true}}, {"id": "osm-13369268471", "name": "Evs", "type": "charging_station", "lat": 43.332277, "lon": 77.007582, "operator": "Unknown", "address": {"street": "", "housenumber": "", "postcode": "", "city": "", "state": "", "country": ""}, "power": {"max_kw": null, "sockets": [], "capacity": 0}, "source": "osm", "tags": {"fee": "yes", "access": "yes", "opening_hours": "", "authentication": "", "brand": "", "network": "", "operator": ""}, "amenities": {"fee": true}}, {"id": "osm-13369268472", "name": "Arilan Energy", "type": "charging_station", "lat": 43.332831, "lon": 77.006103, "operator": "Unknown", "address": {"street": "", "housenumber": "", "postcode": "", "city": "", "state": "", "country": ""}, "power": {"max_kw": null, "sockets": [], "capacity": 0}, "source": "osm", "tags": {"fee": "yes", "access": "", "opening_hours": "", "authentication": "", "brand": "", "network": "", "operator": ""}, "amenities": {"fee": true}}, {"id": "osm-13374078892", "name": "eDrive.kz", "type": "charging_station", "lat": 43.172218, "lon": 77.035482, "operator": "Unknown", "address": {"street": "", "housenumber": "", "postcode": "", "city": "", "state": "", "country": ""}, "power": {"max_kw": null, "sockets": [], "capacity": 0}, "source": "osm", "tags": {"fee": "yes", "access": "", "opening_hours": "", "authentication": "", "brand": "", "network": "", "operator": ""}, "amenities": {"fee": true}}, {"id": "osm-13388551336", "name": "Qazaq Energy Charge", "type": "charging_station", "lat": 43.856226, "lon": 77.041599, "operator": "Qazaq Energy", "address": {"street": "", "housenumber": "", "postcode": "", "city": "", "state": "", "country": ""}, "power": {"max_kw": null, "sockets": [], "capacity": 0}, "source": "osm", "tags": {"fee": "", "access": "", "opening_hours": "", "authentication": "", "brand": "Qazaq Energy Charge", "network": "", "operator": "Qazaq Energy"}, "amenities": {"fee": false}}, {"id": "osm-13388551337", "name": "Qazaq Energy Charge", "type": "charging_station", "lat": 43.855993, "lon": 77.042486, "operator": "Qazaq Energy", "address": {"street": "", "housenumber": "", "postcode": "", "city": "", "state": "", "country": ""}, "power": {"max_kw": null, "sockets": [], "capacity": 0}, "source": "osm", "tags": {"fee": "", "access": "", "opening_hours": "", "authentication": "", "brand": "Qazaq Energy Charge", "network": "", "operator": "Qazaq Energy"}, "amenities": {"fee": false}}, {"id": "osm-13388551346", "name": "Qazaq Energy Charge", "type": "charging_station", "lat": 43.305742, "lon": 77.212305, "operator": "Qazaq Energy", "address": {"street": "", "housenumber": "", "postcode": "", "city": "", "state": "", "country": ""}, "power": {"max_kw": null, "sockets": [], "capacity": 0}, "source": "osm", "tags": {"fee": "", "access": "", "opening_hours": "", "authentication": "", "brand": "Qazaq Energy Charge", "network": "", "operator": "Qazaq Energy"}, "amenities": {"fee": false}}, {"id": "osm-13388551400", "name": "Qazaq Energy Charge", "type": "charging_station", "lat": 43.303218, "lon": 77.06464, "operator": "Qazaq Energy", "address": {"street": "", "housenumber": "", "postcode": "", "city": "", "state": "", "country": ""}, "power": {"max_kw": null, "sockets": [], "capacity": 0}, "source": "osm", "tags": {"fee": "", "access": "", "opening_hours": "", "authentication": "", "brand": "Qazaq Energy Charge", "network": "", "operator": "Qazaq Energy"}, "amenities": {"fee": false}}, {"id": "osm-13388562101", "name": "Qazaq Energy Charge", "type": "charging_station", "lat": 43.292945, "lon": 77.019621, "operator": "Qazaq Energy", "address": {"street": "", "housenumber": "", "postcode": "", "city": "", "state": "", "country": ""}, "power": {"max_kw": null, "sockets": [], "capacity": 0}, "source": "osm", "tags": {"fee": "", "access": "", "opening_hours": "", "authentication": "", "brand": "Qazaq Energy Charge", "network": "", "operator": "Qazaq Energy"}, "amenities": {"fee": false}}, {"id": "osm-13388839346", "name": "Alva", "type": "charging_station", "lat": 43.403019, "lon": 77.028738, "operator": "Unknown", "address": {"street": "", "housenumber": "", "postcode": "", "city": "", "state": "", "country": ""}, "power": {"max_kw": null, "sockets": [], "capacity": 0}, "source": "osm", "tags": {"fee": "yes", "access": "", "opening_hours": "", "authentication": "", "brand": "Alva", "network": "", "operator": ""}, "amenities": {"fee": true}}, {"id": "osm-13388943734", "name": "Arilan Energy", "type": "charging_station", "lat": 43.411877, "lon": 77.018944, "operator": "Arilan Energy", "address": {"street": "", "housenumber": "", "postcode": "", "city": "Отеген батыра", "state": "", "country": ""}, "power": {"max_kw": null, "sockets": [], "capacity": 0}, "source": "osm", "tags": {"fee": "yes", "access": "", "opening_hours": "", "authentication": "", "brand": "Arilan Energy", "network": "", "operator": "Arilan Energy"}, "amenities": {"fee": true}}, {"id": "osm-13388943738", "name": "Arilan Energy", "type": "charging_station", "lat": 43.292231, "lon": 77.016671, "operator": "Arilan Energy", "address": {"street": "улица Райымбек Батыра", "housenumber": "200", "postcode": "", "city": "", "state": "", "country": ""}, "power": {"max_kw": null, "sockets": [], "capacity": 0}, "source": "osm", "tags": {"fee": "yes", "access": "", "opening_hours": "", "authentication": "", "brand": "Arilan Energy", "network": "", "operator": "Arilan Energy"}, "amenities": {"fee": true}}, {"id": "osm-13388943740", "name": "Arilan Energy", "type": "charging_station", "lat": 43.268627, "lon": 77.36423, "operator": "Arilan Energy", "address": {"street": "", "housenumber": "", "postcode": "", "city": "", "state": "", "country": ""}, "power": {"max_kw": null, "sockets": [], "capacity": 0}, "source": "osm", "tags": {"fee": "yes", "access": "", "opening_hours": "", "authentication": "", "brand": "Arilan Energy", "network": "", "operator": "Arilan Energy"}, "amenities": {"fee": true}}, {"id": "osm-13388943744", "name": "Arilan Energy", "type": "charging_station", "lat": 43.404601, "lon": 77.207148, "operator": "Arilan Energy", "address": {"street": "улица Алмерека Абыза", "housenumber": "", "postcode": "", "city": "", "state": "", "country": ""}, "power": {"max_kw": null, "sockets": [], "capacity": 0}, "source": "osm", "tags": {"fee": "yes", "access": "", "opening_hours": "", "authentication": "", "brand": "Arilan Energy", "network": "", "operator": "Arilan Energy"}, "amenities": {"fee": true}}, {"id": "osm-13388943746", "name": "Arilan Energy", "type": "charging_station", "lat": 43.408595, "lon": 77.248115, "operator": "Arilan Energy", "address": {"street": "", "housenumber": "", "postcode": "", "city": "", "state": "", "country": ""}, "power": {"max_kw": null, "sockets": [], "capacity": 0}, "source": "osm", "tags": {"fee": "yes", "access": "", "opening_hours": "", "authentication": "", "brand": "Arilan Energy", "network": "", "operator": "Arilan Energy"}, "amenities": {"fee": true}}, {"id": "osm-13389011539", "name": "EDrive", "type": "charging_station", "lat": 43.287782, "lon": 77.005436, "operator": "EDrive", "address": {"street": "микрорайон Думан -2", "housenumber": "2", "postcode": "", "city": "Алматы", "state": "", "country": ""}, "power": {"max_kw": null, "sockets": [], "capacity": 0}, "source": "osm", "tags": {"fee": "yes", "access": "", "opening_hours": "", "authentication": "", "brand": "EDrive", "network": "", "operator": "EDrive"}, "amenities": {"fee": true}}, {"id": "osm-13390640288", "name": "EVS", "type": "charging_station", "lat": 43.893023, "lon": 77.078423, "operator": "EVS", "address": {"street": "", "housenumber": "41/5", "postcode": "", "city": "", "state": "", "country": ""}, "power": {"max_kw": null, "sockets": [], "capacity": 0}, "source": "osm", "tags": {"fee": "yes", "access": "", "opening_hours": "", "authentication": "", "brand": "EVS", "network": "", "operator": "EVS"}, "amenities": {"fee": true}}, {"id": "osm-13390881690", "name": "MyCharge", "type": "charging_station", "lat": 43.312338, "lon": 77.020133, "operator": "MyCharge", "address": {"street": "", "housenumber": "100/1", "postcode": "", "city": "Алматы", "state": "", "country": ""}, "power": {"max_kw": null, "sockets": [], "capacity": 0}, "source": "osm", "tags": {"fee": "yes", "access": "", "opening_hours": "", "authentication": "", "brand": "MyCharge", "network": "", "operator": "MyCharge"}, "amenities": {"fee": true}}], "count": 23}