{"tile": "poi-tile-36--120", "lat": 36, "lon": -120, "stations": [{"id": "osm-3722138283", "name": "eVgo", "type": "charging_station", "lat": 36.807356, "lon": -119.774781, "operator": "NRG Energy", "address": {"street": "", "housenumber": "", "postcode": "", "city": "", "state": "", "country": ""}, "power": {"max_kw": null, "sockets": [{"type": "Chademo", "kw": null, "count": 1}, {"type": "Type1", "kw": null, "count": 1}, {"type": "Type1 Combo", "kw": null, "count": 2}], "capacity": 4}, "source": "osm", "tags": {"fee": "", "access": "", "opening_hours": "24/7", "authentication": "", "brand": "eVgo", "network": "", "operator": "NRG Energy"}, "amenities": {"fee": false}}, {"id": "osm-3722182757", "name": "eVgo", "type": "charging_station", "lat": 36.739054, "lon": -119.794959, "operator": "NRG Energy", "address": {"street": "", "housenumber": "", "postcode": "", "city": "", "state": "", "country": ""}, "power": {"max_kw": null, "sockets": [{"type": "Type1", "kw": null, "count": 4}], "capacity": 4}, "source": "osm", "tags": {"fee": "", "access": "", "opening_hours": "", "authentication": "", "brand": "", "network": "", "operator": "NRG Energy"}, "amenities": {"fee": false}}, {"id": "osm-6209238247", "name": "Tesla Supercharger", "type": "charging_station", "lat": 36.83546, "lon": -119.91058, "operator": "Tesla", "address": {"street": "North Riverside Drive", "housenumber": "6709", "postcode": "93704", "city": "Fresno", "state": "CA", "country": "US"}, "power": {"max_kw": null, "sockets": [{"type": "Nacs", "kw": null, "count": 10}], "capacity": 10}, "source": "osm", "tags": {"fee": "yes", "access": "customers", "opening_hours": "24/7", "authentication": "", "brand": "Tesla Supercharger", "network": "Supercharger", "operator": "Tesla, Inc."}, "amenities": {"fee": true}}, {"id": "osm-11100050989", "name": "ChargePoint", "type": "charging_station", "lat": 36.297742, "lon": -119.154571, "operator": "ChargePoint", "address": {"street": "", "housenumber": "", "postcode": "", "city": "", "state": "", "country": ""}, "power": {"max_kw": null, "sockets": [{"type": "Type1", "kw": null, "count": 5}], "capacity": 5}, "source": "osm", "tags": {"fee": "yes", "access": "yes", "opening_hours": "", "authentication": "", "brand": "ChargePoint", "network": "", "operator": "ChargePoint"}, "amenities": {"fee": true}}, {"id": "osm-11264852194", "name": "ChargePoint", "type": "charging_station", "lat": 36.812823, "lon": -119.701116, "operator": "ChargePoint", "address": {"street": "", "housenumber": "", "postcode": "", "city": "", "state": "", "country": ""}, "power": {"max_kw": null, "sockets": [], "capacity": 0}, "source": "osm", "tags": {"fee": "", "access": "", "opening_hours": "", "authentication": "", "brand": "ChargePoint", "network": "", "operator": "ChargePoint"}, "amenities": {"fee": false}}, {"id": "osm-11292030756", "name": "Madera Supercharger", "type": "charging_station", "lat": 36.85177, "lon": -119.95209, "operator": "Tesla", "address": {"street": "Avenue 7", "housenumber": "32685", "postcode": "93637", "city": "Madera", "state": "CA", "country": "US"}, "power": {"max_kw": null, "sockets": [{"type": "Nacs", "kw": null, "count": 16}], "capacity": 16}, "source": "osm", "tags": {"fee": "yes", "access": "yes", "opening_hours": "24/7", "authentication": "", "brand": "Tesla Supercharger", "network": "Supercharger", "operator": "Tesla, Inc."}, "amenities": {"fee": true}}, {"id": "osm-11991458063", "name": "Tesla Supercharger", "type": "charging_station", "lat": 36.3508, "lon": -119.4247, "operator": "Tesla", "address": {"street": "Betty Drive", "housenumber": "6603", "postcode": "93291", "city": "Visalia", "state": "CA", "country": "US"}, "power": {"max_kw": null, "sockets": [{"type": "Nacs", "kw": null, "count": 19}], "capacity": 19}, "source": "osm", "tags": {"fee": "yes", "access": "yes", "opening_hours": "24/7", "authentication": "", "brand": "Tesla Supercharger", "network": "Supercharger", "operator": "Tesla, Inc."}, "amenities": {"fee": true}}, {"id": "osm-11991509671", "name": "evconnect", "type": "charging_station", "lat": 36.325359, "lon": -119.391638, "operator": "Unknown", "address": {"street": "", "housenumber": "", "postcode": "", "city": "", "state": "", "country": ""}, "power": {"max_kw": null, "sockets": [], "capacity": 0}, "source": "osm", "tags": {"fee": "yes", "access": "", "opening_hours": "", "authentication": "", "brand": "evconnect", "network": "", "operator": ""}, "amenities": {"fee": true}}, {"id": "osm-11991509672", "name": "Electrify America", "type": "charging_station", "lat": 36.227533, "lon": -119.329976, "operator": "Electrify America", "address": {"street": "", "housenumber": "", "postcode": "", "city": "", "state": "", "country": ""}, "power": {"max_kw": null, "sockets": [], "capacity": 0}, "source": "osm", "tags": {"fee": "yes", "access": "", "opening_hours": "", "authentication": "", "brand": "", "network": "", "operator": "Electrify America"}, "amenities": {"fee": true}}, {"id": "osm-11991509673", "name": "ChargeLab", "type": "charging_station", "lat": 36.222668, "lon": -119.333752, "operator": "Unknown", "address": {"street": "", "housenumber": "", "postcode": "", "city": "", "state": "", "country": ""}, "power": {"max_kw": null, "sockets": [], "capacity": 0}, "source": "osm", "tags": {"fee": "", "access": "", "opening_hours": "", "authentication": "", "brand": "ChargeLab", "network": "", "operator": ""}, "amenities": {"fee": false}}, {"id": "osm-11991509674", "name": "Tesla Destination Charger", "type": "charging_station", "lat": 36.211637, "lon": -119.323578, "operator": "Unknown", "address": {"street": "", "housenumber": "", "postcode": "", "city": "", "state": "", "country": ""}, "power": {"max_kw": null, "sockets": [{"type": "Tesla", "kw": null, "count": 3}], "capacity": 3}, "source": "osm", "tags": {"fee": "no", "access": "customers", "opening_hours": "", "authentication": "", "brand": "Tesla, Inc.", "network": "", "operator": ""}, "amenities": {"fee": false}}, {"id": "osm-11991509675", "name": "EV Charging Station", "type": "charging_station", "lat": 36.207158, "lon": -119.337627, "operator": "Unknown", "address": {"street": "", "housenumber": "", "postcode": "", "city": "", "state": "", "country": ""}, "power": {"max_kw": null, "sockets": [], "capacity": 0}, "source": "osm", "tags": {"fee": "", "access": "", "opening_hours": "", "authentication": "", "brand": "", "network": "", "operator": ""}, "amenities": {"fee": false}}, {"id": "osm-11991509676", "name": "EVConnect", "type": "charging_station", "lat": 36.181514, "lon": -119.330075, "operator": "Unknown", "address": {"street": "", "housenumber": "", "postcode": "", "city": "", "state": "", "country": ""}, "power": {"max_kw": null, "sockets": [], "capacity": 0}, "source": "osm", "tags": {"fee": "", "access": "", "opening_hours": "", "authentication": "", "brand": "EVConnect", "network": "", "operator": ""}, "amenities": {"fee": false}}, {"id": "osm-12463692306", "name": "Caltrans", "type": "charging_station", "lat": 36.107568, "lon": -119.324884, "operator": "Caltrans", "address": {"street": "", "housenumber": "", "postcode": "", "city": "", "state": "", "country": ""}, "power": {"max_kw": null, "sockets": [{"type": "Chademo", "kw": null, "count": 2}, {"type": "Type1 Combo", "kw": null, "count": 2}], "capacity": 4}, "source": "osm", "tags": {"fee": "", "access": "", "opening_hours": "", "authentication": "", "brand": "", "network": "", "operator": "Caltrans"}, "amenities": {"fee": false}}, {"id": "osm-12463692307", "name": "Caltrans", "type": "charging_station", "lat": 36.108244, "lon": -119.32227, "operator": "Caltrans", "address": {"street": "", "housenumber": "", "postcode": "", "city": "", "state": "", "country": ""}, "power": {"max_kw": null, "sockets": [{"type": "Chademo", "kw": null, "count": 2}, {"type": "Type1 Combo", "kw": null, "count": 2}], "capacity": 4}, "source": "osm", "tags": {"fee": "", "access": "", "opening_hours": "", "authentication": "", "brand": "", "network": "", "operator": "Caltrans"}, "amenities": {"fee": false}}, {"id": "osm-12944721991", "name": "Tesla Supercharger", "type": "charging_station", "lat": 36.87174, "lon": -119.7617, "operator": "Tesla", "address": {"street": "East Champlain Drive", "housenumber": "1110", "postcode": "93720", "city": "Fresno", "state": "CA", "country": "US"}, "power": {"max_kw": null, "sockets": [{"type": "Nacs", "kw": null, "count": 16}], "capacity": 16}, "source": "osm", "tags": {"fee": "yes", "access": "yes", "opening_hours": "24/7", "authentication": "", "brand": "Tesla Supercharger", "network": "Supercharger", "operator": "Tesla, Inc."}, "amenities": {"fee": true}}, {"id": "osm-12944743807", "name": "Tesla Supercharger", "type": "charging_station", "lat": 36.84414, "lon": -119.78709, "operator": "Tesla", "address": {"street": "North Blackstone Avenue", "housenumber": "7502", "postcode": "93720", "city": "Fresno", "state": "CA", "country": "US"}, "power": {"max_kw": null, "sockets": [{"type": "Nacs", "kw": null, "count": 12}], "capacity": 12}, "source": "osm", "tags": {"fee": "yes", "access": "yes", "opening_hours": "24/7", "authentication": "", "brand": "Tesla Supercharger", "network": "Supercharger", "operator": "Tesla"}, "amenities": {"fee": true}}, {"id": "osm-12944744111", "name": "Tesla Supercharger", "type": "charging_station", "lat": 36.83216, "lon": -119.90834, "operator": "Tesla", "address": {"street": "North Riverside Drive", "housenumber": "5001", "postcode": "93722", "city": "Fresno", "state": "CA", "country": "US"}, "power": {"max_kw": null, "sockets": [{"type": "Nacs", "kw": null, "count": 12}], "capacity": 12}, "source": "osm", "tags": {"fee": "yes", "access": "yes", "opening_hours": "24/7", "authentication": "", "brand": "Tesla Supercharger", "network": "Supercharger", "operator": "Tesla, Inc."}, "amenities": {"fee": true}}, {"id": "osm-12944744325", "name": "Tesla Supercharger", "type": "charging_station", "lat": 36.8504, "lon": -119.79126, "operator": "Tesla", "address": {"street": "North Blackstone Avenue", "housenumber": "7965", "postcode": "93720", "city": "Fresno", "state": "CA", "country": "US"}, "power": {"max_kw": null, "sockets": [{"type": "Nacs", "kw": null, "count": 8}], "capacity": 8}, "source": "osm", "tags": {"fee": "yes", "access": "yes", "opening_hours": "24/7", "authentication": "", "brand": "Tesla Supercharger", "network": "Supercharger", "operator": "Tesla, Inc."}, "amenities": {"fee": true}}, {"id": "osm-13069130179", "name": "Clovis Supercharger", "type": "charging_station", "lat": 36.837118, "lon": -119.699117, "operator": "Tesla", "address": {"street": "Herndon Avenue", "housenumber": "870", "postcode": "93612", "city": "Clovis", "state": "CA", "country": "US"}, "power": {"max_kw": null, "sockets": [{"type": "Nacs", "kw": null, "count": 12}], "capacity": 12}, "source": "osm", "tags": {"fee": "yes", "access": "customers", "opening_hours": "24/7", "authentication": "", "brand": "Tesla Supercharger", "network": "Supercharger", "operator": "Tesla, Inc."}, "amenities": {"fee": true}}, {"id": "osm-13667871802", "name": "Visalia Supercharger", "type": "charging_station", "lat": 36.297366, "lon": -119.381773, "operator": "Tesla", "address": {"street": "", "housenumber": "", "postcode": "", "city": "", "state": "", "country": ""}, "power": {"max_kw": null, "sockets": [], "capacity": 0}, "source": "osm", "tags": {"fee": "yes", "access": "yes", "opening_hours": "24/7", "authentication": "", "brand": "Tesla Supercharger", "network": "Supercharger", "operator": "Tesla"}, "amenities": {"fee": true}}], "count": 21}